phase_am/__init__.py
phase_am/phase_shift.py
phase_am/utils_camera.py
phase_am/utils_phase_generate.py
phase_am-0.0.11.dist-info/METADATA
phase_am-0.0.11.dist-info/WHEEL
phase_am-0.0.11.dist-info/licenses/LICENSE
phase_am-0.0.11.dist-info/RECORD
