Metadata-Version: 2.3
Name: phase_am
Version: 0.0.11
Summary: Package for FPP in AM
Project-URL: Homepage, https://github.com/Haolinz2/phase_am
Project-URL: Issues, https://github.com/Haolinz2/phase_am/issues
Author-email: Haolin Zhang <haz136@pitt.edu>
License-File: LICENSE
Classifier: License :: OSI Approved :: MIT License
Classifier: Operating System :: OS Independent
Classifier: Programming Language :: Python :: 3
Requires-Python: >=3.8
